theca/__init__.py
theca/_auth.py
theca/_utils.py
theca-2.0.3.dist-info/LICENSE
theca-2.0.3.dist-info/METADATA
theca-2.0.3.dist-info/WHEEL
theca-2.0.3.dist-info/top_level.txt
theca-2.0.3.dist-info/RECORD
