Metadata-Version: 2.1
Name: theca
Version: 2.0.3
Summary: Python library to run your own private CA.
Home-page: https://devnull.cn
Author: Xizhen Du
Author-email: xizhendu@gmail.com
License-File: LICENSE
Requires-Dist: requests ~=2.31.0
Requires-Dist: theid
